script.py
src/__init__.py
src/key_proxy_gui.py
key_proxy-2.1.0.dist-info/LICENSE
key_proxy-2.1.0.dist-info/METADATA
key_proxy-2.1.0.dist-info/WHEEL
key_proxy-2.1.0.dist-info/entry_points.txt
key_proxy-2.1.0.dist-info/top_level.txt
key_proxy-2.1.0.dist-info/RECORD
