Metadata-Version: 2.1
Name: key-proxy
Version: 2.1.0
Summary: UNKNOWN
Home-page: UNKNOWN
License: UNKNOWN
Platform: UNKNOWN
Requires-Python: >=3.7
License-File: LICENSE
Requires-Dist: click
Requires-Dist: kivy
Requires-Dist: plyer
Requires-Dist: pyautogui
Requires-Dist: pyperclip
